orthanc_api_client/__init__.py
orthanc_api_client/api_client.py
orthanc_api_client/capabilities.py
orthanc_api_client/change.py
orthanc_api_client/dicomweb_servers.py
orthanc_api_client/downloaded_instance.py
orthanc_api_client/exceptions.py
orthanc_api_client/helpers.py
orthanc_api_client/helpers_internal.py
orthanc_api_client/http_client.py
orthanc_api_client/instance.py
orthanc_api_client/instances_set.py
orthanc_api_client/job.py
orthanc_api_client/labels_constraint.py
orthanc_api_client/logging.py
orthanc_api_client/modalities.py
orthanc_api_client/patient.py
orthanc_api_client/peers.py
orthanc_api_client/retrieve_method.py
orthanc_api_client/series.py
orthanc_api_client/study.py
orthanc_api_client/tags.py
orthanc_api_client/transfers.py
orthanc_api_client/resources/__init__.py
orthanc_api_client/resources/instances.py
orthanc_api_client/resources/jobs.py
orthanc_api_client/resources/patients.py
orthanc_api_client/resources/resources.py
orthanc_api_client/resources/series_list.py
orthanc_api_client/resources/studies.py
orthanc_api_client-0.22.2.dist-info/licenses/LICENSE.txt
orthanc_api_client-0.22.2.dist-info/METADATA
orthanc_api_client-0.22.2.dist-info/WHEEL
orthanc_api_client-0.22.2.dist-info/top_level.txt
orthanc_api_client-0.22.2.dist-info/RECORD
