Metadata-Version: 2.4
Name: orthanc_api_client
Version: 0.22.2
Summary: Python Orthanc REST API client
Home-page: https://github.com/orthanc-team/python-orthanc-api-client
Author: Orthanc Team
Author-email: info@orthanc.team
Project-URL: Bug Reports, https://github.com/orthanc-team/python-orthanc-api-client/issues
Project-URL: Funding, https://orthanc-team
Project-URL: Source, https://github.com/orthanc-team/python-orthanc-api-client/
Keywords: orthanc,dicom,rest api
Classifier: Development Status :: 3 - Alpha
Classifier: Intended Audience :: Developers
Classifier: License :: OSI Approved :: GNU Lesser General Public License v3 (LGPLv3)
Classifier: Programming Language :: Python :: 3
Classifier: Programming Language :: Python :: 3.8
Classifier: Programming Language :: Python :: 3.9
Classifier: Programming Language :: Python :: 3.10
Classifier: Programming Language :: Python :: 3 :: Only
Requires-Python: >=3.8, <4
License-File: LICENSE.txt
Requires-Dist: requests>=2.31.0
Requires-Dist: pydicom>=3.0.1
Requires-Dist: StrEnum>=0.4.15
Provides-Extra: dev
Requires-Dist: check-manifest; extra == "dev"
Requires-Dist: pytest; extra == "dev"
Provides-Extra: test
Requires-Dist: coverage; extra == "test"
Requires-Dist: pytest; extra == "test"
Dynamic: author
Dynamic: author-email
Dynamic: classifier
Dynamic: description
Dynamic: description-content-type
Dynamic: home-page
Dynamic: keywords
Dynamic: license-file
Dynamic: project-url
Dynamic: provides-extra
Dynamic: requires-dist
Dynamic: requires-python
Dynamic: summary
